odoo10_addon_partner_helper-10.0.0.1.0-py2.7-nspkg.pth
odoo10_addon_partner_helper-10.0.0.1.0.dist-info/top_level.txt
odoo10_addon_partner_helper-10.0.0.1.0.dist-info/WHEEL
odoo10_addon_partner_helper-10.0.0.1.0.dist-info/RECORD
odoo10_addon_partner_helper-10.0.0.1.0.dist-info/metadata.json
odoo10_addon_partner_helper-10.0.0.1.0.dist-info/DESCRIPTION.rst
odoo10_addon_partner_helper-10.0.0.1.0.dist-info/METADATA
odoo10_addon_partner_helper-10.0.0.1.0.dist-info/namespace_packages.txt
odoo/addons/partner_helper/__manifest__.py
odoo/addons/partner_helper/partner.py
odoo/addons/partner_helper/__init__.py
odoo/addons/partner_helper/README.rst
odoo/addons/partner_helper/i18n/es.po
odoo/addons/partner_helper/i18n/sl.po
odoo/addons/partner_helper/i18n/nl.po
odoo/addons/partner_helper/i18n/pt_BR.po
odoo/addons/partner_helper/tests/test_split_address.py
odoo/addons/partner_helper/tests/__init__.py
odoo/addons/partner_helper/static/description/icon.png
