Metadata-Version: 2.0
Name: odoo10-addon-partner-helper
Version: 10.0.0.1.0
Summary: Add specific helper methods
Home-page: http://www.akretion.com/
Author: Akretion,Odoo Community Association (OCA)
Author-email: support@odoo-community.org
License: AGPL-3
Platform: UNKNOWN
Requires-Dist: odoo (<10.1dev,>=10.0)
Classifier: Programming Language :: Python :: 2.7
Classifier: Framework :: Odoo
Classifier: License :: OSI Approved :: GNU Affero General Public License v3
